{
  "$schema": "http://json.schemastore.org/sarif-1.0.0",
  "version": "1.0.0",
  "runs": [
    {
      "tool": {
        "name": "Microsoft (R) Visual C# Compiler",
        "version": "4.2.0.0",
        "fileVersion": "4.2.0-4.22220.5 (432d17a8)",
        "semanticVersion": "4.2.0",
        "language": "en-US"
      },
      "results": [
        {
          "ruleId": "S2068",
          "level": "warning",
          "message": "\"password\" detected here, make sure this is not a hard-coded credential.",
          "locations": [
            {
              "resultFile": {
                "uri": "file:///C:/Users/34626/source/repos/SoleusHotel/SoleusHotelApi/SoleusHotelApi/Constants/SwaggerDescriptions/HotelUserControllerDescriptions.cs",
                "region": {
                  "startLine": 13,
                  "startColumn": 29,
                  "endLine": 13,
                  "endColumn": 97
                }
              }
            }
          ],
          "properties": {
            "warningLevel": 1
          }
        },
        {
          "ruleId": "S2068",
          "level": "warning",
          "message": "\"password\" detected here, make sure this is not a hard-coded credential.",
          "locations": [
            {
              "resultFile": {
                "uri": "file:///C:/Users/34626/source/repos/SoleusHotel/SoleusHotelApi/SoleusHotelApi/Constants/SwaggerDescriptions/HotelUserControllerDescriptions.cs",
                "region": {
                  "startLine": 16,
                  "startColumn": 29,
                  "endLine": 16,
                  "endColumn": 99
                }
              }
            }
          ],
          "properties": {
            "warningLevel": 1
          }
        },
        {
          "ruleId": "S3267",
          "level": "warning",
          "message": "Loop should be simplified by calling Select(item => item.Ticks))",
          "locations": [
            {
              "resultFile": {
                "uri": "file:///C:/Users/34626/source/repos/SoleusHotel/SoleusHotelApi/SoleusHotelApi/Extensions/TimeSpanExtensions.cs",
                "region": {
                  "startLine": 13,
                  "startColumn": 34,
                  "endLine": 13,
                  "endColumn": 40
                }
              }
            }
          ],
          "properties": {
            "warningLevel": 1
          }
        }
      ],
      "rules": {
        "S2068": {
          "id": "S2068",
          "shortDescription": "Hard-coded credentials are security-sensitive",
          "fullDescription": "Because it is easy to extract strings from an application source code or binary, credentials should not be hard-coded. This is particularly true for applications that are distributed or that are open-source.",
          "defaultLevel": "warning",
          "helpUri": "https://rules.sonarsource.com/csharp/RSPEC-2068",
          "properties": {
            "category": "Blocker Security Hotspot",
            "isEnabledByDefault": true,
            "tags": [
              "C#",
              "MainSourceScope",
              "SonarWay"
            ]
          }
        },
        "S3267": {
          "id": "S3267",
          "shortDescription": "Loops should be simplified with \"LINQ\" expressions",
          "fullDescription": "When a loop is filtering, selecting or aggregating, those functions can be handled with a clearer, more concise LINQ expression instead.",
          "defaultLevel": "warning",
          "helpUri": "https://rules.sonarsource.com/csharp/RSPEC-3267",
          "properties": {
            "category": "Minor Code Smell",
            "isEnabledByDefault": true,
            "tags": [
              "C#",
              "MainSourceScope",
              "SonarWay"
            ]
          }
        }
      }
    }
  ]
}